bigredbutton/__init__.py
bigredbutton/apps.py
bigredbutton/templates/bigredbutton/qsessions_list.html
bigredbutton/templates/bigredbutton/user_sessions_list.html
bigredbutton/templatetags/user_agent_str.py
bigredbutton/urls.py
bigredbutton/views.py
django_bigredbutton-0.3.2.dist-info/METADATA
django_bigredbutton-0.3.2.dist-info/WHEEL
django_bigredbutton-0.3.2.dist-info/licenses/LICENSE.txt
django_bigredbutton-0.3.2.dist-info/RECORD
