Metadata-Version: 2.4
Name: django-bigredbutton
Version: 0.3.2
Summary: Django app that offers a big red button to sign out of all other user sessions
License-File: LICENSE.txt
Author: blag
Author-email: blag@users.noreply.github.com
Requires-Python: >=3.11
Classifier: Development Status :: 5 - Production/Stable
Classifier: Environment :: Web Environment
Classifier: Framework :: Django
Classifier: Framework :: Django :: 4.0
Classifier: Framework :: Django :: 4.1
Classifier: Framework :: Django :: 4.2
Classifier: Intended Audience :: Developers
Classifier: License :: OSI Approved :: MIT License
Classifier: Operating System :: OS Independent
Classifier: Programming Language :: Python
Classifier: Programming Language :: Python :: 3
Classifier: Programming Language :: Python :: 3.11
Classifier: Programming Language :: Python :: 3.12
Classifier: Programming Language :: Python :: 3.13
Classifier: Programming Language :: Python :: 3.14
Classifier: Topic :: Internet :: WWW/HTTP :: Session
Classifier: Topic :: Security
Requires-Dist: django (>=4.0)
Requires-Dist: user-agents (>=2.2.0)
